pulumi_archive/__init__.py
pulumi_archive/_inputs.py
pulumi_archive/_utilities.py
pulumi_archive/file.py
pulumi_archive/get_file.py
pulumi_archive/outputs.py
pulumi_archive/provider.py
pulumi_archive/pulumi-plugin.json
pulumi_archive/py.typed
pulumi_archive-0.3.6.dist-info/METADATA
pulumi_archive-0.3.6.dist-info/WHEEL
pulumi_archive-0.3.6.dist-info/top_level.txt
pulumi_archive-0.3.6.dist-info/RECORD
